setup.py
easycordey/main.py
easycordey.egg-info/PKG-INFO
easycordey.egg-info/SOURCES.txt
easycordey.egg-info/dependency_links.txt
easycordey.egg-info/top_level.txt